[
    {
        "image_url": "https://d1w8cc2yygc27j.cloudfront.net/-3077499948772834306/-8035656563553479907.jpg",
        "date": "9/24/2021",
        "price": "$66.00",
        "grade": "9",
        "lot_number": "154614909989",
        "auction_house": "eBay",
        "auction_seller": "irviocho_0",
        "auction_type": "Auction",
        "cert_number": "49289986"
    },
    {
        "image_url": "https://d1w8cc2yygc27j.cloudfront.net/-3077499948772834306/-8035656563553479907.jpg",
        "date": "9/24/2021",
        "price": "$66.00",
        "grade": "9",
        "lot_number": "154614909989",
        "auction_house": "eBay",
        "auction_seller": "irviocho_0",
        "auction_type": "Auction",
        "cert_number": "49289986"
    }
]