[
    {
        "image_url": "https://d1w8cc2yygc27j.cloudfront.net/-6652690876888646425/-5350591834112359043.jpg",
        "date": "7/16/2024",
        "price": "$81.00",
        "grade": "6",
        "lot_number": "315556872573",
        "auction_house": "eBay",
        "auction_seller": "mason_991",
        "auction_type": "Auction",
        "cert_number": "83551493"
    },
    {
        "image_url": "https://d1w8cc2yygc27j.cloudfront.net/-7544548242586855329/-6664921077308551616.jpg",
        "date": "7/7/2024",
        "price": "$380.00",
        "grade": "7",
        "lot_number": "364974939769",
        "auction_house": "eBay",
        "auction_seller": "vabeachsales75",
        "auction_type": "Auction",
        "cert_number": "91436808"
    },
    {
        "image_url": "https://d1w8cc2yygc27j.cloudfront.net/3018742933667809859/-7791101379678584365.jpg",
        "date": "6/28/2024",
        "price": "$202.50",
        "grade": "6",
        "lot_number": "355811770107",
        "auction_house": "eBay",
        "auction_seller": "collectables_and_more",
        "auction_type": "Auction",
        "cert_number": "91260154"
    },
    {
        "image_url": "https://d1w8cc2yygc27j.cloudfront.net/2883002051246568528/-1216506115153840856.jpg",
        "date": "1/28/2024",
        "price": "$405.00",
        "grade": "5",
        "lot_number": "285659644212",
        "auction_house": "eBay",
        "auction_seller": "zandgemporium",
        "auction_type": "Auction",
        "cert_number": "63949247"
    },
    {
        "image_url": "https://d1w8cc2yygc27j.cloudfront.net/-6390259714669929532/-1030441328402951803.jpg",
        "date": "12/12/2023",
        "price": "$202.50",
        "grade": "3",
        "lot_number": "335150293935",
        "auction_house": "eBay",
        "auction_seller": "wolters03",
        "auction_type": "Auction",
        "cert_number": "50965269"
    },
    {
        "image_url": "https://d1w8cc2yygc27j.cloudfront.net/4875671409089089642/5296029632425172303.jpg",
        "date": "7/7/2023",
        "price": "$808.00",
        "grade": "9",
        "lot_number": "374783389647",
        "auction_house": "eBay",
        "auction_seller": "probstein123",
        "auction_type": "Auction",
        "cert_number": "76130555"
    },
    {
        "image_url": "https://d1w8cc2yygc27j.cloudfront.net/1418737598718184679/4566106707451353240.jpg",
        "date": "2/28/2023",
        "price": "$439.25",
        "grade": "7",
        "lot_number": "314415201848",
        "auction_house": "eBay",
        "auction_seller": "zaccur_81",
        "auction_type": "Auction",
        "cert_number": "72250373"
    },
    {
        "image_url": "https://d1w8cc2yygc27j.cloudfront.net/-3684891588560034240/8107316394052286147.jpg",
        "date": "12/13/2022",
        "price": "$135.50",
        "grade": "5",
        "lot_number": "374390115979",
        "auction_house": "eBay",
        "auction_seller": "probstein123",
        "auction_type": "Auction",
        "cert_number": "68208732"
    },
    {
        "image_url": "https://d1w8cc2yygc27j.cloudfront.net/-8149591857199058458/-8561902575775017796.jpg",
        "date": "12/15/2021",
        "price": "$815.00",
        "grade": "7",
        "lot_number": "185199223580",
        "auction_house": "eBay",
        "auction_seller": "acclear",
        "auction_type": "Auction",
        "cert_number": "62100292"
    },
    {
        "image_url": "https://d1w8cc2yygc27j.cloudfront.net/-4724192066165358468/1858345169606498104.jpg",
        "date": "10/20/2021",
        "price": "$360.00",
        "grade": "5",
        "lot_number": "154645534144",
        "auction_house": "eBay",
        "auction_seller": "hometowncollectibiles",
        "auction_type": "Auction",
        "cert_number": "57593221"
    },
    {
        "image_url": "https://d1w8cc2yygc27j.cloudfront.net/7432935992796747287/-4743619147002768853.jpg",
        "date": "8/12/2021",
        "price": "$460.00",
        "grade": "6",
        "lot_number": "184985519430",
        "auction_house": "eBay",
        "auction_seller": "acclear",
        "auction_type": "Auction",
        "cert_number": "62220620"
    },
    {
        "image_url": "https://d1w8cc2yygc27j.cloudfront.net/7989428537271362908/2853473576212185704.jpg",
        "date": "8/9/2021",
        "price": "$798.88",
        "grade": "8",
        "lot_number": "144132762595",
        "auction_house": "eBay",
        "auction_seller": "n20397",
        "auction_type": "Auction",
        "cert_number": "59307526"
    },
    {
        "image_url": "https://d1w8cc2yygc27j.cloudfront.net/1516612143044803036/-4175932768705439744.jpg",
        "date": "8/6/2021",
        "price": "$2,955.00",
        "grade": "9",
        "lot_number": "184971034211",
        "auction_house": "eBay",
        "auction_seller": "acclear",
        "auction_type": "Auction",
        "cert_number": "62194020"
    },
    {
        "image_url": "https://d1w8cc2yygc27j.cloudfront.net/8963828138277387975/692576133793986026.jpg",
        "date": "8/4/2021",
        "price": "$685.00",
        "grade": "7",
        "lot_number": "184971027607",
        "auction_house": "eBay",
        "auction_seller": "acclear",
        "auction_type": "Auction",
        "cert_number": "54211483"
    },
    {
        "image_url": "https://d1w8cc2yygc27j.cloudfront.net/-5747727243892604066/-562876072237859119.jpg",
        "date": "7/16/2021",
        "price": "$306.50",
        "grade": "5",
        "lot_number": "184939244961",
        "auction_house": "eBay",
        "auction_seller": "acclear",
        "auction_type": "Auction",
        "cert_number": "59034961"
    },
    {
        "image_url": "https://d1w8cc2yygc27j.cloudfront.net/-7620453623476867344/-8157246288125285521.jpg",
        "date": "7/3/2021",
        "price": "$578.00",
        "grade": "8",
        "lot_number": "353549767154",
        "auction_house": "eBay",
        "auction_seller": "kingdomsstuff",
        "auction_type": "Auction",
        "cert_number": "62161483"
    },
    {
        "image_url": "https://d1w8cc2yygc27j.cloudfront.net/1888725302415459714/-9120228721100485230.jpg",
        "date": "5/29/2021",
        "price": "$464.00",
        "grade": "6",
        "lot_number": "144043798192",
        "auction_house": "eBay",
        "auction_seller": "pwcc_auctions",
        "auction_type": "Auction",
        "cert_number": "55322022"
    },
    {
        "image_url": "https://d1w8cc2yygc27j.cloudfront.net/-6759993122865926624/-5986783907398433942.jpg",
        "date": "4/12/2021",
        "price": "$1,500.00",
        "grade": "6",
        "lot_number": "363354109935",
        "auction_house": "eBay",
        "auction_seller": "eternal_sad",
        "auction_type": "Best Offer",
        "cert_number": "55322022"
    },
    {
        "image_url": "https://d1w8cc2yygc27j.cloudfront.net/-7209912958195085775/8631369367259324974.jpg",
        "date": "3/8/2021",
        "price": "$1,655.00",
        "grade": "7",
        "lot_number": "114709630932",
        "auction_house": "eBay",
        "auction_seller": "seed702",
        "auction_type": "Auction",
        "cert_number": "54211483"
    },
    {
        "image_url": "https://d1w8cc2yygc27j.cloudfront.net/-6652690876888646425/-5350591834112359043.jpg",
        "date": "7/16/2024",
        "price": "$81.00",
        "grade": "6",
        "lot_number": "315556872573",
        "auction_house": "eBay",
        "auction_seller": "mason_991",
        "auction_type": "Auction",
        "cert_number": "83551493"
    },
    {
        "image_url": "https://d1w8cc2yygc27j.cloudfront.net/-7544548242586855329/-6664921077308551616.jpg",
        "date": "7/7/2024",
        "price": "$380.00",
        "grade": "7",
        "lot_number": "364974939769",
        "auction_house": "eBay",
        "auction_seller": "vabeachsales75",
        "auction_type": "Auction",
        "cert_number": "91436808"
    },
    {
        "image_url": "https://d1w8cc2yygc27j.cloudfront.net/3018742933667809859/-7791101379678584365.jpg",
        "date": "6/28/2024",
        "price": "$202.50",
        "grade": "6",
        "lot_number": "355811770107",
        "auction_house": "eBay",
        "auction_seller": "collectables_and_more",
        "auction_type": "Auction",
        "cert_number": "91260154"
    },
    {
        "image_url": "https://d1w8cc2yygc27j.cloudfront.net/2883002051246568528/-1216506115153840856.jpg",
        "date": "1/28/2024",
        "price": "$405.00",
        "grade": "5",
        "lot_number": "285659644212",
        "auction_house": "eBay",
        "auction_seller": "zandgemporium",
        "auction_type": "Auction",
        "cert_number": "63949247"
    },
    {
        "image_url": "https://d1w8cc2yygc27j.cloudfront.net/-6390259714669929532/-1030441328402951803.jpg",
        "date": "12/12/2023",
        "price": "$202.50",
        "grade": "3",
        "lot_number": "335150293935",
        "auction_house": "eBay",
        "auction_seller": "wolters03",
        "auction_type": "Auction",
        "cert_number": "50965269"
    },
    {
        "image_url": "https://d1w8cc2yygc27j.cloudfront.net/4875671409089089642/5296029632425172303.jpg",
        "date": "7/7/2023",
        "price": "$808.00",
        "grade": "9",
        "lot_number": "374783389647",
        "auction_house": "eBay",
        "auction_seller": "probstein123",
        "auction_type": "Auction",
        "cert_number": "76130555"
    },
    {
        "image_url": "https://d1w8cc2yygc27j.cloudfront.net/1418737598718184679/4566106707451353240.jpg",
        "date": "2/28/2023",
        "price": "$439.25",
        "grade": "7",
        "lot_number": "314415201848",
        "auction_house": "eBay",
        "auction_seller": "zaccur_81",
        "auction_type": "Auction",
        "cert_number": "72250373"
    },
    {
        "image_url": "https://d1w8cc2yygc27j.cloudfront.net/-3684891588560034240/8107316394052286147.jpg",
        "date": "12/13/2022",
        "price": "$135.50",
        "grade": "5",
        "lot_number": "374390115979",
        "auction_house": "eBay",
        "auction_seller": "probstein123",
        "auction_type": "Auction",
        "cert_number": "68208732"
    },
    {
        "image_url": "https://d1w8cc2yygc27j.cloudfront.net/-8149591857199058458/-8561902575775017796.jpg",
        "date": "12/15/2021",
        "price": "$815.00",
        "grade": "7",
        "lot_number": "185199223580",
        "auction_house": "eBay",
        "auction_seller": "acclear",
        "auction_type": "Auction",
        "cert_number": "62100292"
    },
    {
        "image_url": "https://d1w8cc2yygc27j.cloudfront.net/-4724192066165358468/1858345169606498104.jpg",
        "date": "10/20/2021",
        "price": "$360.00",
        "grade": "5",
        "lot_number": "154645534144",
        "auction_house": "eBay",
        "auction_seller": "hometowncollectibiles",
        "auction_type": "Auction",
        "cert_number": "57593221"
    },
    {
        "image_url": "https://d1w8cc2yygc27j.cloudfront.net/7432935992796747287/-4743619147002768853.jpg",
        "date": "8/12/2021",
        "price": "$460.00",
        "grade": "6",
        "lot_number": "184985519430",
        "auction_house": "eBay",
        "auction_seller": "acclear",
        "auction_type": "Auction",
        "cert_number": "62220620"
    },
    {
        "image_url": "https://d1w8cc2yygc27j.cloudfront.net/7989428537271362908/2853473576212185704.jpg",
        "date": "8/9/2021",
        "price": "$798.88",
        "grade": "8",
        "lot_number": "144132762595",
        "auction_house": "eBay",
        "auction_seller": "n20397",
        "auction_type": "Auction",
        "cert_number": "59307526"
    },
    {
        "image_url": "https://d1w8cc2yygc27j.cloudfront.net/1516612143044803036/-4175932768705439744.jpg",
        "date": "8/6/2021",
        "price": "$2,955.00",
        "grade": "9",
        "lot_number": "184971034211",
        "auction_house": "eBay",
        "auction_seller": "acclear",
        "auction_type": "Auction",
        "cert_number": "62194020"
    },
    {
        "image_url": "https://d1w8cc2yygc27j.cloudfront.net/8963828138277387975/692576133793986026.jpg",
        "date": "8/4/2021",
        "price": "$685.00",
        "grade": "7",
        "lot_number": "184971027607",
        "auction_house": "eBay",
        "auction_seller": "acclear",
        "auction_type": "Auction",
        "cert_number": "54211483"
    },
    {
        "image_url": "https://d1w8cc2yygc27j.cloudfront.net/-5747727243892604066/-562876072237859119.jpg",
        "date": "7/16/2021",
        "price": "$306.50",
        "grade": "5",
        "lot_number": "184939244961",
        "auction_house": "eBay",
        "auction_seller": "acclear",
        "auction_type": "Auction",
        "cert_number": "59034961"
    },
    {
        "image_url": "https://d1w8cc2yygc27j.cloudfront.net/-7620453623476867344/-8157246288125285521.jpg",
        "date": "7/3/2021",
        "price": "$578.00",
        "grade": "8",
        "lot_number": "353549767154",
        "auction_house": "eBay",
        "auction_seller": "kingdomsstuff",
        "auction_type": "Auction",
        "cert_number": "62161483"
    },
    {
        "image_url": "https://d1w8cc2yygc27j.cloudfront.net/1888725302415459714/-9120228721100485230.jpg",
        "date": "5/29/2021",
        "price": "$464.00",
        "grade": "6",
        "lot_number": "144043798192",
        "auction_house": "eBay",
        "auction_seller": "pwcc_auctions",
        "auction_type": "Auction",
        "cert_number": "55322022"
    },
    {
        "image_url": "https://d1w8cc2yygc27j.cloudfront.net/-6759993122865926624/-5986783907398433942.jpg",
        "date": "4/12/2021",
        "price": "$1,500.00",
        "grade": "6",
        "lot_number": "363354109935",
        "auction_house": "eBay",
        "auction_seller": "eternal_sad",
        "auction_type": "Best Offer",
        "cert_number": "55322022"
    },
    {
        "image_url": "https://d1w8cc2yygc27j.cloudfront.net/-7209912958195085775/8631369367259324974.jpg",
        "date": "3/8/2021",
        "price": "$1,655.00",
        "grade": "7",
        "lot_number": "114709630932",
        "auction_house": "eBay",
        "auction_seller": "seed702",
        "auction_type": "Auction",
        "cert_number": "54211483"
    }
]