[
    {
        "image_url": "https://d1w8cc2yygc27j.cloudfront.net/-8713880814116758429/8076969321990925751.jpg",
        "date": "3/13/2023",
        "price": "$12.98",
        "grade": "9",
        "lot_number": "256006133517",
        "auction_house": "eBay",
        "auction_seller": "venusaur_island",
        "auction_type": "Auction",
        "cert_number": "71084494"
    },
    {
        "image_url": "https://d1w8cc2yygc27j.cloudfront.net/-8713880814116758429/8076969321990925751.jpg",
        "date": "3/13/2023",
        "price": "$12.98",
        "grade": "9",
        "lot_number": "256006133517",
        "auction_house": "eBay",
        "auction_seller": "venusaur_island",
        "auction_type": "Auction",
        "cert_number": "71084494"
    }
]