[
    {
        "auction_seller": "honestant321",
        "price": "$15.70",
        "image_url": "https://d1w8cc2yygc27j.cloudfront.net/-5080264822921719283/-6621495791563005228.jpg",
        "cert_number": "62546249",
        "grade": "9",
        "lot_number": "134451323943",
        "auction_type": "Auction",
        "auction_house": "eBay",
        "date": "2/22/2023"
    },
    {
        "auction_seller": "tea..tea",
        "price": "$49.00",
        "lot_number": "363520282202",
        "date": "9/2/2021",
        "cert_number": "62546249",
        "grade": "9",
        "auction_type": "Auction",
        "image_url": "https://d1w8cc2yygc27j.cloudfront.net/-7053666267972310295/5224163017600406698.jpg",
        "auction_house": "eBay"
    },
    {
        "lot_number": "304790218476",
        "cert_number": "65199452",
        "image_url": "https://d1w8cc2yygc27j.cloudfront.net/-9076962622382343868/9162528343818542116.jpg",
        "price": "$32.75",
        "auction_seller": "guandb0",
        "auction_type": "Auction",
        "auction_house": "eBay",
        "grade": "10",
        "date": "2/9/2023"
    },
    {
        "auction_seller": "bd-tcg",
        "lot_number": "364182509415",
        "date": "3/25/2023",
        "grade": "8",
        "cert_number": "71933247",
        "image_url": "https://d1w8cc2yygc27j.cloudfront.net/2046535770692089672/7055357483991484409.jpg",
        "price": "$11.50",
        "auction_type": "Auction",
        "auction_house": "eBay"
    },
    {
        "date": "4/1/2023",
        "cert_number": "68903260",
        "price": "$23.50",
        "auction_seller": "orbtradingcards",
        "lot_number": "175664643288",
        "auction_type": "Auction",
        "auction_house": "eBay",
        "image_url": "https://d1w8cc2yygc27j.cloudfront.net/-707877461536950508/5746834964476310939.jpg",
        "grade": "10"
    },
    {
        "price": "$26.00",
        "auction_seller": "wiraa_48",
        "image_url": "https://d1w8cc2yygc27j.cloudfront.net/-7178085953735054446/-4576344667336323762.jpg",
        "auction_type": "Auction",
        "cert_number": "94130335",
        "auction_house": "eBay",
        "grade": "10",
        "lot_number": "315594992346",
        "date": "8/1/2024"
    },
    {
        "date": "7/25/2024",
        "lot_number": "365013134529",
        "image_url": "https://d1w8cc2yygc27j.cloudfront.net/-453621264844889135/298441397528658526.jpg",
        "auction_seller": "nickel_city_collectibles",
        "price": "$40.00",
        "auction_type": "Auction",
        "cert_number": "69303155",
        "auction_house": "eBay",
        "grade": "10"
    },
    {
        "date": "6/27/2023",
        "auction_seller": "dylanewma_6",
        "grade": "9",
        "cert_number": "70952740",
        "auction_type": "Auction",
        "auction_house": "eBay",
        "lot_number": "325700859635",
        "price": "$12.50",
        "image_url": "https://d1w8cc2yygc27j.cloudfront.net/8440469826261683799/3077738633664765067.jpg"
    },
    {
        "image_url": "https://d1w8cc2yygc27j.cloudfront.net/-1429733107324259299/-4743691475842357474.jpg",
        "lot_number": "387089314088",
        "price": "$41.00",
        "auction_type": "Auction",
        "auction_house": "eBay",
        "grade": "10",
        "auction_seller": "tylerm_2525",
        "date": "6/24/2024",
        "cert_number": "91892444"
    },
    {
        "auction_seller": "comc_consignment",
        "cert_number": "66592167",
        "image_url": "https://d1w8cc2yygc27j.cloudfront.net/6822344404224809143/4143734996585889549.jpg",
        "grade": "10",
        "price": "$36.00",
        "date": "1/10/2023",
        "auction_type": "Auction",
        "auction_house": "eBay",
        "lot_number": "234838251861"
    },
    {
        "image_url": "https://d1w8cc2yygc27j.cloudfront.net/-3685213953240413872/5591480063218348420.jpg",
        "auction_seller": "tea..tea",
        "cert_number": "62546249",
        "grade": "9",
        "date": "12/28/2022",
        "auction_type": "Auction",
        "price": "$11.02",
        "auction_house": "eBay",
        "lot_number": "364086086624"
    },
    {
        "cert_number": "65244482",
        "date": "12/24/2022",
        "image_url": "https://d1w8cc2yygc27j.cloudfront.net/6988133151699070635/3468294538338481018.jpg",
        "auction_house": "eBay",
        "price": "$32.99",
        "auction_type": "Auction",
        "lot_number": "394378192187",
        "grade": "10",
        "auction_seller": "chasingthecase"
    },
    {
        "image_url": "https://d1w8cc2yygc27j.cloudfront.net/-5713717178813172175/-2644159070992942375.jpg",
        "lot_number": "285210014897",
        "cert_number": "71795752",
        "auction_seller": "joskick-3",
        "price": "$32.00",
        "auction_type": "Auction",
        "auction_house": "eBay",
        "date": "4/4/2023",
        "grade": "10"
    },
    {
        "cert_number": "75347423",
        "auction_seller": "metaverse_cards",
        "date": "6/6/2024",
        "image_url": "https://d1w8cc2yygc27j.cloudfront.net/2104302842830294150/660955527280922460.jpg",
        "auction_type": "Auction",
        "lot_number": "156235409624",
        "auction_house": "eBay",
        "grade": "10",
        "price": "$16.50"
    },
    {
        "cert_number": "92059209",
        "auction_seller": "alovedove46",
        "date": "7/1/2024",
        "grade": "9",
        "price": "$11.50",
        "image_url": "https://d1w8cc2yygc27j.cloudfront.net/-7708538330215734532/3517971367901048777.jpg",
        "auction_type": "Auction",
        "auction_house": "eBay",
        "lot_number": "276517559733"
    },
    {
        "cert_number": "82543600",
        "date": "12/7/2023",
        "lot_number": "355247189329",
        "image_url": "https://d1w8cc2yygc27j.cloudfront.net/-2366682988207759556/8278662602198364904.jpg",
        "grade": "8",
        "price": "$9.99",
        "auction_seller": "korkhouse21",
        "auction_type": "Auction",
        "auction_house": "eBay"
    },
    {
        "auction_seller": "taylors_trade",
        "grade": "8",
        "image_url": "https://d1w8cc2yygc27j.cloudfront.net/7764267418140932703/-4646851874686804647.jpg",
        "date": "2/17/2023",
        "auction_type": "Auction",
        "auction_house": "eBay",
        "cert_number": "69504021",
        "lot_number": "175607378365",
        "price": "$16.50"
    },
    {
        "price": "$9.50",
        "image_url": "https://d1w8cc2yygc27j.cloudfront.net/4793805707485254729/4465603879785770299.jpg",
        "cert_number": "85991394",
        "grade": "9",
        "auction_seller": "3brotherssportscards",
        "date": "4/2/2024",
        "auction_type": "Auction",
        "auction_house": "eBay",
        "lot_number": "256458458561"
    },
    {
        "price": "$38.00",
        "lot_number": "204267138139",
        "date": "3/8/2023",
        "image_url": "https://d1w8cc2yygc27j.cloudfront.net/6342334793114181440/5566233866198982884.jpg",
        "cert_number": "67149761",
        "auction_type": "Auction",
        "auction_seller": "darkchapel86",
        "auction_house": "eBay",
        "grade": "10"
    },
    {
        "date": "7/28/2024",
        "price": "$26.00",
        "image_url": "https://d1w8cc2yygc27j.cloudfront.net/-7845254917692078099/-4424044986263993425.jpg",
        "lot_number": "285966290774",
        "auction_seller": "zandgemporium",
        "auction_type": "Auction",
        "cert_number": "66784860",
        "auction_house": "eBay",
        "grade": "10"
    }
]