[
    {
        "image_url": "https://d1w8cc2yygc27j.cloudfront.net/7971819435145194269/-5863207727318504568.jpg",
        "lot_number": "115573630846",
        "auction_seller": "tannah12",
        "grade": "9",
        "price": "$24.17",
        "auction_type": "Auction",
        "date": "10/30/2022",
        "auction_house": "eBay",
        "cert_number": "60221452"
    },
    {
        "date": "10/18/2022",
        "price": "$4.25",
        "cert_number": "57740607",
        "image_url": "https://d1w8cc2yygc27j.cloudfront.net/3471427051431870368/-2276319237486978110.jpg",
        "grade": "6",
        "auction_seller": "probstein123",
        "auction_type": "Auction",
        "auction_house": "eBay",
        "lot_number": "374299401582"
    }
]