[
    {
        "lot_number": "387116279783",
        "image_url": "https://d1w8cc2yygc27j.cloudfront.net/2595322780132129051/-9016564249972788250.jpg",
        "date": "7/2/2024",
        "grade": "9",
        "auction_seller": "probstein123",
        "cert_number": "89818229",
        "auction_type": "Auction",
        "price": "$28.00",
        "auction_house": "eBay"
    },
    {
        "cert_number": "68587746",
        "grade": "8",
        "date": "12/28/2022",
        "price": "$19.99",
        "image_url": "https://d1w8cc2yygc27j.cloudfront.net/3772753478364829047/-5353566052570850131.jpg",
        "auction_type": "Auction",
        "auction_seller": "krukcards",
        "auction_house": "eBay",
        "lot_number": "364086147976"
    },
    {
        "image_url": "https://d1w8cc2yygc27j.cloudfront.net/-7520219649429501061/918946575150907612.jpg",
        "price": "$102.50",
        "auction_seller": "itemland",
        "cert_number": "43851200",
        "lot_number": "166654312194",
        "date": "3/25/2024",
        "auction_type": "Auction",
        "auction_house": "eBay",
        "grade": "10"
    },
    {
        "lot_number": "305727716775",
        "cert_number": "93090589",
        "image_url": "https://d1w8cc2yygc27j.cloudfront.net/893765592454587387/565179000986387699.jpg",
        "grade": "8",
        "date": "8/19/2024",
        "auction_type": "Auction",
        "auction_seller": "mytcgshopsd",
        "price": "$24.50",
        "auction_house": "eBay"
    },
    {
        "image_url": "https://d1w8cc2yygc27j.cloudfront.net/625709991060346265/7031754630411022720.jpg",
        "date": "9/18/2019",
        "price": "$10.00",
        "grade": "9",
        "auction_seller": "probstein123",
        "lot_number": "362752004879",
        "auction_type": "Auction",
        "cert_number": "43355080",
        "auction_house": "eBay"
    },
    {
        "cert_number": "40771476",
        "grade": "8",
        "image_url": "https://d1w8cc2yygc27j.cloudfront.net/-631020211716239483/383086101421233952.jpg",
        "auction_type": "Auction",
        "auction_seller": "literaryscholar",
        "lot_number": "142836549214",
        "auction_house": "eBay",
        "date": "6/24/2018",
        "price": "$0.99"
    },
    {
        "date": "5/6/2024",
        "lot_number": "166737042725",
        "cert_number": "43851200",
        "auction_seller": "itemland",
        "price": "$120.50",
        "image_url": "https://d1w8cc2yygc27j.cloudfront.net/-6355663437925912968/8045693498126768921.jpg",
        "auction_type": "Auction",
        "auction_house": "eBay",
        "grade": "10"
    },
    {
        "cert_number": "82453777",
        "date": "6/11/2024",
        "grade": "8",
        "price": "$29.00",
        "lot_number": "126514684484",
        "auction_seller": "isthisloaded",
        "auction_house": "eBay",
        "auction_type": "Auction",
        "image_url": "https://d1w8cc2yygc27j.cloudfront.net/-8014843368616158820/5369704930461552290.jpg"
    },
    {
        "lot_number": "124858842239",
        "date": "8/29/2021",
        "auction_seller": "card_secret",
        "grade": "9",
        "price": "$44.00",
        "cert_number": "50453620",
        "image_url": "https://d1w8cc2yygc27j.cloudfront.net/-1599126476690022300/-2329229356809939853.jpg",
        "auction_type": "Auction",
        "auction_house": "eBay"
    }
]